<?xml version="1.0" encoding="UTF-8"?>
<sv:node xmlns:sv="http://www.jcp.org/jcr/sv/1.0" sv:name="error">
  <sv:property sv:name="jcr:primaryType" sv:type="Name">
    <sv:value>hst:component</sv:value>
  </sv:property>
  <sv:property sv:name="jcr:uuid" sv:type="String">
    <sv:value>3d742030-904e-4eb5-aee8-18af1e1e4051</sv:value>
  </sv:property>
  <sv:property sv:name="hst:referencecomponent" sv:type="String">
    <sv:value>hst:pages/simplepage</sv:value>
  </sv:property>
  <sv:node sv:name="main">
    <sv:property sv:name="jcr:primaryType" sv:type="Name">
      <sv:value>hst:component</sv:value>
    </sv:property>
    <sv:property sv:name="jcr:uuid" sv:type="String">
      <sv:value>319fef75-09d7-4858-9348-23138ba52ff3</sv:value>
    </sv:property>
    <sv:node sv:name="content">
      <sv:property sv:name="jcr:primaryType" sv:type="Name">
        <sv:value>hst:component</sv:value>
      </sv:property>
      <sv:property sv:name="jcr:uuid" sv:type="String">
        <sv:value>fb932632-e67a-4922-bce0-c9a54235dec6</sv:value>
      </sv:property>
      <sv:property sv:name="hst:componentclassname" sv:type="String">
        <sv:value>com.onehippo.gogreen.components.search.ErrorSearchComponent</sv:value>
      </sv:property>
      <sv:property sv:name="hst:parameternames" sv:type="String" sv:multiple="true">
        <sv:value>pageSize</sv:value>
      </sv:property>
      <sv:property sv:name="hst:parametervalues" sv:type="String" sv:multiple="true">
        <sv:value>3</sv:value>
      </sv:property>
      <sv:property sv:name="hst:template" sv:type="String">
        <sv:value>search.results</sv:value>
      </sv:property>
    </sv:node>
    <sv:node sv:name="right">
      <sv:property sv:name="jcr:primaryType" sv:type="Name">
        <sv:value>hst:component</sv:value>
      </sv:property>
      <sv:property sv:name="jcr:uuid" sv:type="String">
        <sv:value>d802abae-abcf-4356-b627-24fe4cd1a2af</sv:value>
      </sv:property>
      <sv:property sv:name="hst:template" sv:type="String">
        <sv:value>error.right</sv:value>
      </sv:property>
    </sv:node>
  </sv:node>
</sv:node>
